{
    "type": "minecraft:crafting_shaped",
   
    "pattern":
    [
        "OAO",
        "TDT",
        "OOO"
    ],
   
    "key":
    {
        "A":
        {
            "item": "trackersmod:antenne"
        },
        "O":
        {
            "item": "minecraft:obsidian"
        },
        "D":
        {
            "item": "minecraft:diamond"
        },
        "T":
        {
            "item": "trackersmod:anti_tracker"
        }
    },
   
    "result":
    {
        "item": "trackersmod:brouiller",
        "count": 2
    }
}